ed_auth/__init__.py
ed_auth/application/__init__.py
ed_auth/application/common/__init__.py
ed_auth/application/common/responses/__init__.py
ed_auth/application/common/responses/base_response.py
ed_auth/application/contracts/__init__.py
ed_auth/application/contracts/infrastructure/__init__.py
ed_auth/application/contracts/infrastructure/abc_api.py
ed_auth/application/contracts/infrastructure/abc_email_templater.py
ed_auth/application/contracts/infrastructure/abc_rabbitmq_producer.py
ed_auth/application/features/__init__.py
ed_auth/application/features/auth/__init__.py
ed_auth/application/features/auth/dtos/__init__.py
ed_auth/application/features/auth/dtos/create_or_get_user_dto.py
ed_auth/application/features/auth/dtos/create_user_dto.py
ed_auth/application/features/auth/dtos/create_user_verify_dto.py
ed_auth/application/features/auth/dtos/delete_user_dto.py
ed_auth/application/features/auth/dtos/login_user_dto.py
ed_auth/application/features/auth/dtos/login_user_verify_dto.py
ed_auth/application/features/auth/dtos/logout_dto.py
ed_auth/application/features/auth/dtos/unverified_user_dto.py
ed_auth/application/features/auth/dtos/update_user_dto.py
ed_auth/application/features/auth/dtos/user_dto.py
ed_auth/application/features/auth/dtos/verify_token_dto.py
ed_auth/application/features/auth/dtos/validators/__init__.py
ed_auth/application/features/auth/dtos/validators/create_user_dto_validator.py
ed_auth/application/features/auth/dtos/validators/create_user_verify_dto_validator.py
ed_auth/application/features/auth/dtos/validators/login_user_dto_validator.py
ed_auth/application/features/auth/dtos/validators/login_user_verify_dto_validator.py
ed_auth/application/features/auth/dtos/validators/update_user_dto_validator.py
ed_auth/application/features/auth/handlers/__init__.py
ed_auth/application/features/auth/handlers/commands/__init__.py
ed_auth/application/features/auth/handlers/commands/create_or_get_user_command_handler.py
ed_auth-0.2.10.dist-info/licenses/LICENSE
ed_auth-0.2.10.dist-info/METADATA
ed_auth-0.2.10.dist-info/WHEEL
ed_auth-0.2.10.dist-info/top_level.txt
ed_auth-0.2.10.dist-info/RECORD
